ocrd_fork_dinglehopper-0.0.1-nspkg.pth
qurator/dinglehopper/__init__.py
qurator/dinglehopper/align.py
qurator/dinglehopper/character_error_rate.py
qurator/dinglehopper/cli.py
qurator/dinglehopper/cli_extract.py
qurator/dinglehopper/config.py
qurator/dinglehopper/edit_distance.py
qurator/dinglehopper/extracted_text.py
qurator/dinglehopper/ocr_files.py
qurator/dinglehopper/ocrd-tool.json
qurator/dinglehopper/ocrd_cli.py
qurator/dinglehopper/word_error_rate.py
qurator/dinglehopper/templates/report.html.j2
qurator/dinglehopper/templates/report.html.js
qurator/dinglehopper/templates/report.json.j2
ocrd_fork_dinglehopper-0.0.1.dist-info/LICENSE
ocrd_fork_dinglehopper-0.0.1.dist-info/METADATA
ocrd_fork_dinglehopper-0.0.1.dist-info/WHEEL
ocrd_fork_dinglehopper-0.0.1.dist-info/entry_points.txt
ocrd_fork_dinglehopper-0.0.1.dist-info/namespace_packages.txt
ocrd_fork_dinglehopper-0.0.1.dist-info/top_level.txt
ocrd_fork_dinglehopper-0.0.1.dist-info/RECORD
