Metadata-Version: 2.1
Name: ocrd-fork-dinglehopper
Version: 0.0.1
Summary: The OCR evaluation tool
Home-page: UNKNOWN
Author: Mike Gerber, The QURATOR SPK Team
Author-email: mike.gerber@sbb.spk-berlin.de, qurator@sbb.spk-berlin.de
License: Apache
Keywords: qurator ocr
Platform: UNKNOWN
Requires-Dist: MarkupSafe
Requires-Dist: attrs
Requires-Dist: click
Requires-Dist: colorama
Requires-Dist: jinja2
Requires-Dist: lxml
Requires-Dist: multimethod (==1.3)
Requires-Dist: numpy
Requires-Dist: ocrd (>=2.20.1)
Requires-Dist: tqdm
Requires-Dist: uniseg
